[{"banque":"Centrale-Supélec","epreuve":"Maths 1 2019","partie":"Partie III","questions":"1 q. : Q20","difficulte":"Standard","intitule":"Vérification qu'un commutant est une sous-algèbre","corrections":[{"question":"Q20","correction":"$\\mathcal{C}(f) \\subset \\mathcal{L}(E)$ et $\\mathcal{C}(f) \\neq \\emptyset$ car $\\mathrm{Id} \\circ f = f = f \\circ \\mathrm{Id}$, donc $\\mathrm{Id} \\in \\mathcal{C}(f)$. Stabilité par combinaison linéaire : si $g_1, g_2 \\in \\mathcal{C}(f)$ et $\\alpha, \\beta \\in \\mathbb{K}$, alors $f \\circ (\\alpha g_1 + \\beta g_2) = \\alpha f \\circ g_1 + \\beta f \\circ g_2 = \\alpha g_1 \\circ f + \\beta g_2 \\circ f = (\\alpha g_1 + \\beta g_2) \\circ f$. Stabilité par composition : si $g_1, g_2 \\in \\mathcal{C}(f)$, alors $f \\circ (g_1 \\circ g_2) = (f \\circ g_1) \\circ g_2 = (g_1 \\circ f) \\circ g_2 = g_1 \\circ (f \\circ g_2) = g_1 \\circ (g_2 \\circ f) = (g_1 \\circ g_2) \\circ f$. Donc $\\mathcal{C}(f)$ est une sous-algèbre de $\\mathcal{L}(E)$."}]},{"banque":"X-ENS","epreuve":"Maths 1 2023","partie":"Partie I","questions":"1 q. : 1","difficulte":"Standard","intitule":"Vérification des axiomes de sous-algèbre et inversibilité via la transconjuguée","corrections":[]},{"banque":"X-ENS","epreuve":"Maths 1 2023","partie":"Partie IV","questions":"5 q. : 20b, 21, 24b, 24c, 27","difficulte":"Intermédiaire／Standard","intitule":"Identification de la sous-algèbre $\\mathbb{R} + \\mathbb{R}x$ à $\\mathbb{C}$ ; Existence d'une racine carrée de $-1$ dans une algèbre non isomorphe à $\\mathbb{R}$ ou $\\mathbb{C}$ ; Le carré de $\\beta$ est un réel strictement négatif ; Construction de l'isomorphisme $A \\simeq \\mathbb{H}$ via la base $(1, i_A, j_A, k_A)$ ; Démonstration du théorème C (classification des algèbres normées à norme multiplicative)","corrections":[]},{"banque":"X-ENS","epreuve":"Maths 2 2023","partie":"Partie I","questions":"1 q. : 7","difficulte":"Intermédiaire","intitule":"Intégrité de l'anneau des fonctions DSE via le principe des zéros isolés","corrections":[]}]